jool_exporter.py
jool_exporter-25.3.8.dist-info/LICENSE
jool_exporter-25.3.8.dist-info/METADATA
jool_exporter-25.3.8.dist-info/WHEEL
jool_exporter-25.3.8.dist-info/entry_points.txt
jool_exporter-25.3.8.dist-info/top_level.txt
jool_exporter-25.3.8.dist-info/RECORD
