Metadata-Version: 2.2
Name: jool-exporter
Version: 25.3.8
Summary: Export `jool stats display` for prometheus
Home-page: http://github.com/cooperlees/jool-exporter
Author: Cooper Lees
Author-email: me@cooperlees.com
License: BSD
Classifier: Development Status :: 3 - Alpha
Classifier: License :: OSI Approved :: BSD License
Classifier: Programming Language :: Python :: 3
Classifier: Programming Language :: Python :: 3 :: Only
Requires-Python: >=3.8
License-File: LICENSE
Requires-Dist: prometheus_client
Dynamic: author
Dynamic: author-email
Dynamic: classifier
Dynamic: description
Dynamic: description-content-type
Dynamic: home-page
Dynamic: license
Dynamic: requires-dist
Dynamic: requires-python
Dynamic: summary
